{
    "installed": {
        "client_id": "362327116008-s84t091me56g2vb812ho3pl0mssfgagn.apps.googleusercontent.com",
        "project_id": "driveapp-359312",
        "auth_uri": "https://accounts.google.com/o/oauth2/auth",
        "token_uri": "https://oauth2.googleapis.com/token",
        "auth_provider_x509_cert_url": "https://www.googleapis.com/oauth2/v1/certs",
        "client_secret": "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",
        "redirect_uris": [
            "REPLACEMEurl"
        ]
    }
}